ctrs/__init__.py
ctrs/setup.py
ctrs/layers/__init__.py
ctrs/layers/layer.py
ctrs/models/__init__.py
ctrs/models/deepfm.py
ctrs/models/fm.py
CTRs-0.0.10.dist-info/LICENSE
CTRs-0.0.10.dist-info/METADATA
CTRs-0.0.10.dist-info/WHEEL
CTRs-0.0.10.dist-info/top_level.txt
CTRs-0.0.10.dist-info/RECORD
