Metadata-Version: 2.1
Name: CTRs
Version: 0.0.10
Summary: A package for CTR prediction
Home-page: https://github.com/TimJLS/CTRs
Author: Tim Su
Author-email: omg80827@gmail.com
License: UNKNOWN
Project-URL: Bug Tracker, https://github.com/TimJLS/CTRs/issues
Platform: UNKNOWN
Classifier: Programming Language :: Python :: 3
Classifier: License :: OSI Approved :: MIT License
Classifier: Operating System :: OS Independent
Requires-Python: >=3.6
Requires-Dist: tensorflow (>=2)
